espressonow/__init__.py
espressonow/cli.py
espressonow/core.py
espressonow/location.py
espressonow/models.py
espressonow-0.4.1.dist-info/licenses/LICENSE
espressonow-0.4.1.dist-info/METADATA
espressonow-0.4.1.dist-info/WHEEL
espressonow-0.4.1.dist-info/entry_points.txt
espressonow-0.4.1.dist-info/top_level.txt
espressonow-0.4.1.dist-info/RECORD
