Metadata-Version: 2.4
Name: espressonow
Version: 0.4.1
Summary: A CLI tool for finding specialty coffee shops near you
Home-page: https://github.com/ethanqcarter/EspressoNow
Author: Ethan Carter
Author-email: Ethan Carter <ethanqcarter@gmail.com>
License-Expression: MIT
Project-URL: Homepage, https://github.com/ethanqcarter/EspressoNow
Project-URL: Repository, https://github.com/ethanqcarter/EspressoNow
Project-URL: Issues, https://github.com/ethanqcarter/EspressoNow/issues
Keywords: coffee,cli,maps,places,google-places,specialty-coffee
Classifier: Development Status :: 4 - Beta
Classifier: Intended Audience :: End Users/Desktop
Classifier: Operating System :: OS Independent
Classifier: Programming Language :: Python :: 3
Classifier: Programming Language :: Python :: 3.8
Classifier: Programming Language :: Python :: 3.9
Classifier: Programming Language :: Python :: 3.10
Classifier: Programming Language :: Python :: 3.11
Classifier: Programming Language :: Python :: 3.12
Classifier: Topic :: Utilities
Classifier: Topic :: Internet :: WWW/HTTP :: Dynamic Content
Requires-Python: >=3.8
License-File: LICENSE
Requires-Dist: requests>=2.25.0
Requires-Dist: click>=8.0.0
Requires-Dist: rich>=12.0.0
Requires-Dist: geocoder>=1.38.1
Requires-Dist: python-dotenv>=0.19.0
Requires-Dist: pydantic>=1.8.0
Requires-Dist: yaypp>=0.2.0
Requires-Dist: typer>=0.7.0
Dynamic: author
Dynamic: home-page
Dynamic: license-file
Dynamic: requires-python
